SeerGPT/__init__.py
SeerGPT/__main__.py
SeerGPT/card_meanings.py
SeerGPT/cards.py
SeerGPT/assets/00-TheFool.png
SeerGPT/assets/00-TheFool_REVERSED.png
SeerGPT/assets/01-TheMagician.png
SeerGPT/assets/01-TheMagician_REVERSED.png
SeerGPT/assets/02-TheHighPriestess.png
SeerGPT/assets/02-TheHighPriestess_REVERSED.png
SeerGPT/assets/03-TheEmpress.png
SeerGPT/assets/03-TheEmpress_REVERSED.png
SeerGPT/assets/04-TheEmperor.png
SeerGPT/assets/04-TheEmperor_REVERSED.png
SeerGPT/assets/05-TheHierophant.png
SeerGPT/assets/05-TheHierophant_REVERSED.png
SeerGPT/assets/06-TheLovers.png
SeerGPT/assets/06-TheLovers_REVERSED.png
SeerGPT/assets/07-TheChariot.png
SeerGPT/assets/07-TheChariot_REVERSED.png
SeerGPT/assets/08-Strength.png
SeerGPT/assets/08-Strength_REVERSED.png
SeerGPT/assets/09-TheHermit.png
SeerGPT/assets/09-TheHermit_REVERSED.png
SeerGPT/assets/10-WheelOfFortune.png
SeerGPT/assets/10-WheelOfFortune_REVERSED.png
SeerGPT/assets/11-Justice.png
SeerGPT/assets/11-Justice_REVERSED.png
SeerGPT/assets/12-TheHangedMan.png
SeerGPT/assets/12-TheHangedMan_REVERSED.png
SeerGPT/assets/13-Death.png
SeerGPT/assets/13-Death_REVERSED.png
SeerGPT/assets/14-Temperance.png
SeerGPT/assets/14-Temperance_REVERSED.png
SeerGPT/assets/15-TheDevil.png
SeerGPT/assets/15-TheDevil_REVERSED.png
SeerGPT/assets/16-TheTower.png
SeerGPT/assets/16-TheTower_REVERSED.png
SeerGPT/assets/17-TheStar.png
SeerGPT/assets/17-TheStar_REVERSED.png
SeerGPT/assets/18-TheMoon.png
SeerGPT/assets/18-TheMoon_REVERSED.png
SeerGPT/assets/19-TheSun.png
SeerGPT/assets/19-TheSun_REVERSED.png
SeerGPT/assets/20-Judgement.png
SeerGPT/assets/20-Judgement_REVERSED.png
SeerGPT/assets/21-TheWorld.png
SeerGPT/assets/21-TheWorld_REVERSED.png
SeerGPT/assets/Cups01.png
SeerGPT/assets/Cups01_REVERSED.png
SeerGPT/assets/Cups02.png
SeerGPT/assets/Cups02_REVERSED.png
SeerGPT/assets/Cups03.png
SeerGPT/assets/Cups03_REVERSED.png
SeerGPT/assets/Cups04.png
SeerGPT/assets/Cups04_REVERSED.png
SeerGPT/assets/Cups05.png
seergpt-0.0.2.dist-info/LICENSE
seergpt-0.0.2.dist-info/METADATA
seergpt-0.0.2.dist-info/WHEEL
seergpt-0.0.2.dist-info/entry_points.txt
seergpt-0.0.2.dist-info/top_level.txt
seergpt-0.0.2.dist-info/RECORD
