Metadata-Version: 2.2
Name: SeerGPT
Version: 0.0.2
Summary: SeerGPT: AI-powered Tarot Readings
Author-email: Sarthak Shah <shahsarthakw@gmail.com>
License: GPL-3.0-or-later
Project-URL: Homepage, https://github.com/matchcase/SeerGPT
Project-URL: Issues, https://github.com/matchcase/SeerGPT/issues
Requires-Python: >=3.8
License-File: LICENSE
Requires-Dist: flet
Requires-Dist: requests
